{
  "date": "2026-03-01",
  "sessionCount": 5,
  "sessions": [
    {
      "n": 1,
      "time": "06:35",
      "account": "holotaco",
      "type": "creator",
      "engagement": "full",
      "status": "confirmed",
      "done": false
    },
    {
      "n": 2,
      "time": "11:49",
      "account": "OPI_PRODUCTS",
      "type": "nail-brand",
      "engagement": "full",
      "status": "confirmed",
      "done": false
    },
    {
      "n": 3,
      "time": "13:17",
      "account": "essie",
      "type": "nail-brand",
      "engagement": "full",
      "status": "confirmed",
      "done": false
    },
    {
      "n": 4,
      "time": "16:34",
      "account": "ORLYbeauty",
      "type": "nail-brand",
      "engagement": "full",
      "status": "verify",
      "done": false
    },
    {
      "n": 5,
      "time": "20:48",
      "account": "IGK_hair",
      "type": "hair-brand",
      "engagement": "like-only",
      "status": "verify",
      "done": false
    }
  ]
}